{"wantWatch":[],"watching":[{"title":"天使降临到我身边","type":"番剧","area":"日本","cover":"https://i0.hdslb.com/bfs/bangumi/e1015a803ad97406f9eddfbc6ad608cc965f8b05.png","totalCount":"全13话","id":4316442,"follow":"428.2 万","view":"9848.1 万","danmaku":"227.7 万","coin":"67.9 万","score":9.8,"des":"怕生的御宅族女大学生宫子，遇到了天使般的小学生！？在看到妹妹带来的新朋友小花的瞬间，宫子就无法抑制住心跳！！她为了和小花成为朋友而奋斗，但……“想要和超绝可爱的她做朋友”系小品喜剧，开幕！...","progress":false,"ep_status":false,"new_ep":13},{"title":"憨豆先生动画版 第四季（上） 中文配音","type":"番剧","area":"英国","cover":"https://i0.hdslb.com/bfs/bangumi/image/c885ff2643e066d0736fd3295f374bc3a6c042ad.jpg","totalCount":"全26话","id":26813055,"follow":2041,"view":"43.6 万","danmaku":264,"coin":186,"score":"-","des":"《憨豆先生》动画版携52集全新剧集重磅回归第四季！我们将继续跟随憨豆先生、他最好的伙伴泰迪熊以及脾气暴躁的女房东威科特夫人，见证憨豆日常生活中的各种乌龙趣事。他身边依然有长期忍受他搞怪行为的女友厄玛、...","progress":false,"ep_status":false,"new_ep":26},{"title":"大耳朵图图--小小欢乐魔法师 ","type":"国创","area":"中国大陆","cover":"https://i0.hdslb.com/bfs/bangumi/image/7ff5e27a17dad03ad1ce55ad208262547e268b52.png","totalCount":"全26话","id":28230335,"follow":"14.8 万","view":"3308.4 万","danmaku":"21.1 万","coin":"2.6 万","score":9.8,"des":"《图图》讲述了三岁小男孩胡图图快乐成长中的点滴故事，内容健康幽默童真 童趣。故事涉及了幼儿生长的每一个领域，关注孩子和父母们关心的每一个话题。整个剧集的故事在喜剧的形式下，藏着孩子们愿意接受的道理，揭...","progress":false,"ep_status":false,"new_ep":26},{"title":"斗龙战士","type":"国创","area":"中国大陆","cover":"https://i0.hdslb.com/bfs/bangumi/image/33c65289c7df70f6c7af5ff5c42fa8a43011013e.png","totalCount":"全60话","id":26878745,"follow":4421,"view":"673.8 万","danmaku":"22.5 万","coin":"2.8 万","score":"-","des":"在恐龙世纪，一颗陨石碰撞地球，造成一场大爆炸，这场大爆炸形成了一个裂缝空间，此空间就是斗龙世界。斗龙世界由四大神王龙守护着，但是邪恶的力量不断出现，黑暗之王黑亡龙诞生了，带给斗龙世界战争和毁灭，为了封...","progress":false,"ep_status":false,"new_ep":60},{"title":"京剧猫 第二季","type":"国创","area":"中国大陆","cover":"https://i0.hdslb.com/bfs/bangumi/2a0e27beb89bb7e0b1a0a574ef6021fc936877ab.jpg","totalCount":"全52话","id":6400,"follow":"47.5 万","view":"8199.1 万","danmaku":"69.1 万","coin":"12.4 万","score":9.8,"des":"无父无母的主角白糖，年幼时曾被京剧猫所救，立誓长大要成为伟大的京剧猫。而后它结识了星罗班的京剧猫末裔武崧、小青、大飞，并加入星罗班拜金婆婆和唐明为师。白糖没有名门血统，但天赋过人，它依靠惊人的努力和永...","progress":false,"ep_status":false,"new_ep":52},{"title":"蜡笔小新 第八季（中文）","type":"番剧","area":"日本","cover":"https://i0.hdslb.com/bfs/bangumi/image/549116c113858d907cd9ee420c1d97127d2c9edc.jpg","totalCount":"全84话","id":21981326,"follow":"291.9 万","view":"8786.7 万","danmaku":"7.0 万","coin":"5.7 万","score":9.5,"des":"野原新之助今年5岁了，他人小鬼大，富于幻想，喜欢别出心裁。他和父亲、母亲、妹妹组成一个幸福的四口之家，他还收养了一条像棉花糖一样的流浪狗——小白。小新的妈妈是一位全职主妇，粗心而又有点神经质的她经常被...","progress":false,"ep_status":false,"new_ep":84},{"title":"聪明的顺溜","type":"国创","area":"中国大陆","cover":"https://i0.hdslb.com/bfs/bangumi/9efeb644224c9ebb47bfbdebec04c3da2ef15151.jpg","totalCount":"全52话","id":28222338,"follow":"7.8 万","view":"1104.3 万","danmaku":"5.4 万","coin":"1.3 万","score":9.5,"des":"动漫电视剧《聪明的顺溜》以强国梦、强军梦为大的时代背景，以部队军事斗争准备生动实践和基层火热生活为基本素材，通过描述“顺溜”和他的战友们这些新生代士兵在训练演习、工作生活中，用机智克服困难、用妙招帮助...","progress":false,"ep_status":false,"new_ep":52},{"title":"喜羊羊与灰太狼","type":"国创","area":"中国大陆","cover":"https://i0.hdslb.com/bfs/bangumi/image/4cd5d75b3ac57d30a114bbe21a9dacd4f7c2fa81.png","totalCount":"全530话","id":21827044,"follow":"185.6 万","view":"8821.6 万","danmaku":"10.4 万","coin":"8.8 万","score":9.8,"des":"羊历3131年，青青草原上，羊羊族群十分兴旺发达，羊羊们在这里幸福地生活着。直到灰太狼带着妻子红太狼搬到对岸的森林，羊羊们才真正在现实中见到书上记载的狼。\n灰太狼每天想尽办法要跨越铁栅栏抓羊，但他没想...","progress":false,"ep_status":false,"new_ep":530},{"title":"西游记","type":"国创","area":"中国大陆","cover":"https://i0.hdslb.com/bfs/bangumi/image/3f4a3329c104b99595f724ea6b07a199f40f215b.jpg","totalCount":"全52话","id":21129033,"follow":"12.6 万","view":"2218.2 万","danmaku":"3.6 万","coin":"2.1 万","score":9.8,"des":"本片重现了孙悟空和他的两个师弟猪八戒和沙僧共同保护师傅唐僧，由东土大唐去西天取经的过程。师徒四人沿途历尽千辛万苦、斗妖降魔、披荆斩棘，经历九九八十一难取回真经，终于修成正果，为孩子们展示了一个充满想象...","progress":false,"ep_status":false,"new_ep":52},{"title":"哪吒传奇","type":"国创","area":"中国大陆","cover":"https://i0.hdslb.com/bfs/bangumi/image/a9c49eeb3cbdb228c30b39881b54a3ce897c5a93.png","totalCount":"全52话","id":24403439,"follow":"7.2 万","view":"747.2 万","danmaku":"4.8 万","coin":"1.3 万","score":9.9,"des":"这部集神话、童话、传奇于一体的大型动画连续剧，讲述了小英雄哪吒成长的故事。大魔头石矶潜伏千年，伺机向正义力量反扑，她帮助残暴的纣王镇压天下的民众。正义力量期待着一个英雄的诞生，而石矶为了自己的阴谋，开...","progress":false,"ep_status":false,"new_ep":52},{"title":"正义红师","type":"国创","area":"中国大陆","cover":"https://i0.hdslb.com/bfs/bangumi/96c638d686a881fbeb3679a456a506bcf5e8545d.jpg","totalCount":"全52话","id":3402,"follow":"15.2 万","view":"815.9 万","danmaku":"18.0 万","coin":"3.3 万","score":9.8,"des":"《正义红师》是由中国人民解放军八一电影制片厂和深圳市方块动漫画文化发展有限公司联合出品的二维加三维高水准动画。这部国内首部以科幻军事题材为背景的动画片，主要讲述中国军人在遇到来自外星未知威胁时，使用高...","progress":false,"ep_status":false,"new_ep":52},{"title":"成龙历险记","type":"番剧","area":"美国","cover":"https://i0.hdslb.com/bfs/bangumi/image/22afe34a7ee7b28aa45ea1bc0d5c326836c5e8b7.png","totalCount":"全95话","id":28344676,"follow":"28.9 万","view":"4428.8 万","danmaku":"6.0 万","coin":"2.6 万","score":9.1,"des":"剧情讲述了成龙一家有趣的历险故事，成龙和小玉在世界各地探索各种神秘悬疑的谜团，生活和经历中充满着许多奇幻色彩，其中有关武功和魔法，包含了亲情和友情，以及中国文化的元素。成龙的职业是一位考古专家，但事实...","progress":false,"ep_status":false,"new_ep":95},{"title":"虹猫蓝兔七侠传","type":"国创","area":"中国大陆","cover":"https://i0.hdslb.com/bfs/bangumi/c084f6378c9bb7002cad5e6a31092a36624c7f63.jpg","totalCount":"全108话","id":5366,"follow":"97.4 万","view":"7556.1 万","danmaku":"161.8 万","coin":"22.8 万","score":9.9,"des":"       公元347年，风景秀丽的张家界，以黑心虎为首的魔教放火烧山，荼毒生灵，企图抓森林之灵兽麒麟，妄图借喝麒麟的热血以增强内力，称霸武林。为了维护森林的和平与安宁，虹猫的父亲（白猫）联合蓝兔的...","progress":false,"ep_status":false,"new_ep":108},{"title":"天官赐福 第二季","type":"国创","area":"中国大陆","cover":"https://i0.hdslb.com/bfs/bangumi/image/6ee51928451a6e716975a13088a6df06a31fe9b5.jpg","totalCount":"-","id":28235383,"follow":"851.0 万","view":"1.1 亿","danmaku":"35.2 万","coin":"52.9 万","score":"-","des":"半月关之事告一段落，谢怜受神武大帝君吾的传唤回天庭述职，却意外得知有神官在鬼市附近施法求救。而鬼市如今的主人“血雨探花”花城，正是七日前突然辞别的红衣少年三郎。此事疑点重重，谢怜自愿请命，与风师青玄、...","progress":false,"ep_status":false,"new_ep":-1},{"title":"成龙历险记 中文配音","type":"番剧","area":"美国","cover":"https://i0.hdslb.com/bfs/bangumi/image/22afe34a7ee7b28aa45ea1bc0d5c326836c5e8b7.png","totalCount":"全95话","id":20261822,"follow":"94.5 万","view":"2.1 亿","danmaku":"33.2 万","coin":"16.2 万","score":8.8,"des":"剧情讲述了成龙一家有趣的历险故事，成龙和小玉在世界各地探索各种神秘悬疑的谜团，生活和经历中充满着许多奇幻色彩，其中有关武功和魔法，包含了亲情和友情，以及中国文化的元素。成龙的职业是一位考古专家，但事实...","progress":false,"ep_status":false,"new_ep":95},{"title":"京剧猫","type":"国创","area":"中国大陆","cover":"https://i0.hdslb.com/bfs/bangumi/241a0cde9188af2a09cec47a9cffe57116d2b2d9.jpg","totalCount":"全60话","id":5885,"follow":"98.0 万","view":"1.5 亿","danmaku":"119.4 万","coin":"62.2 万","score":9.8,"des":"且看白糖和星罗班的小伙伴如何披荆斩棘战胜邪恶。","progress":false,"ep_status":false,"new_ep":60},{"title":"熊出没","type":"国创","area":"中国大陆","cover":"https://i0.hdslb.com/bfs/bangumi/image/fb6ca695ef8e93ea8cd8fde26ecddd2278cb1d8b.png","totalCount":"全52话","id":21185045,"follow":"36.0 万","view":"9749.3 万","danmaku":"23.5 万","coin":"11.2 万","score":9.5,"des":"宁静祥和的东北原始森林，空气清新，万物复苏。熊大和熊二两兄弟在林间追逐奔跑，非常快乐。正在此时，发动机的轰鸣打破了森林的宁静，来者是一个伐木队的小老板，他叫光头强。光头强带着老板的重托，竟来到风景优美...","progress":false,"ep_status":false,"new_ep":52},{"title":"狐妖小红娘","type":"国创","area":"中国大陆","cover":"https://i0.hdslb.com/bfs/bangumi/cbb20ee03e97a9f3ad2e1506a10fd1271f1c584a.jpg","totalCount":"全100话","id":2543,"follow":"761.3 万","view":"10.0 亿","danmaku":"1173.5 万","coin":"283.4 万","score":9.5,"des":"根据古典小说记载，世上有人有妖，妖会与人相恋，妖寿命千年，人的寿命有限，人死了，妖活着。人会投胎转世，但投胎以后不记得上辈子的爱。妖如果痴情的话，就去找狐妖“购买”一项服务，让投胎转世的人回忆起前世的...","progress":false,"ep_status":false,"new_ep":100},{"title":"灵笼 第二季","type":"国创","area":"中国大陆","cover":"https://i0.hdslb.com/bfs/bangumi/image/08bf0c1e24e454de51b58d1e26c0a9aecbe9b0c1.png","totalCount":"全12话","id":21123554,"follow":"1048.6 万","view":"2.9 亿","danmaku":"206.3 万","coin":"347.7 万","score":9.7,"des":"【第5集起大会员专享】\n数百年前，欲望催生了几乎灭绝人类的玛娜生态。人类瞬间沦为猎物，文明毁灭殆尽，末日中猜忌和恐惧拉开了人与人之间的距离。灾难当前，人们逐渐意识到：情感——这个被灯塔视为禁忌的存在，...","progress":false,"ep_status":false,"new_ep":12},{"title":"克雷瓦提斯-魔兽之王与婴儿与尸之勇者-","type":"番剧","area":"日本","cover":"https://i0.hdslb.com/bfs/bangumi/image/6179b0449be273e4146f25d671ed1115ddae3962.png","totalCount":"全12话","id":26638078,"follow":"19.8 万","view":"401.0 万","danmaku":"1.7 万","coin":"1.3 万","score":9.8,"des":"阿莉西亚从小就向往着成为勇者，最终被国王选中成为13名勇者之一。勇者们带着传说中的宝剑前去讨伐魔兽王克雷瓦提斯。但如此鲁莽的举动，为艾多西亚大陆的人族惹来了可能导致灭绝的危机。全世界的唯一希望，就是被...","progress":false,"ep_status":false,"new_ep":12}],"watched":[]}